__init__.py
wocecolor.py
wocecolormap-0.0.1.dist-info/LICENSE
wocecolormap-0.0.1.dist-info/METADATA
wocecolormap-0.0.1.dist-info/WHEEL
wocecolormap-0.0.1.dist-info/top_level.txt
wocecolormap-0.0.1.dist-info/RECORD
